ZjjLab_tools/__init__.py
ZjjLab_tools/version.py
ZjjLab_tools/utils/__init__.py
ZjjLab_tools/utils/dcm_tonii.py
ZjjLab_tools-0.0.3.dist-info/LICENSE.txt
ZjjLab_tools-0.0.3.dist-info/METADATA
ZjjLab_tools-0.0.3.dist-info/WHEEL
ZjjLab_tools-0.0.3.dist-info/top_level.txt
ZjjLab_tools-0.0.3.dist-info/RECORD
