Metadata-Version: 2.1
Name: ZjjLab_tools
Version: 0.0.3
Summary: preprocess for MRI of brain
Author: ZauberZ
Classifier: Programming Language :: Python :: 3
Classifier: License :: OSI Approved :: MIT License
Classifier: Operating System :: OS Independent
Requires-Python: >=3.8
License-File: LICENSE.txt
